ALU/alu_design.v
module ALU (
    input wire [31:0] operandA,  // First operand
    input wire [31:0] operandB,  // Second operand
    input wire [3:0] aluOp,      // 4-bit opcode for operation selection
    input wire shiftAmount,      // Shift amount (0 or 1)
    input wire enable,
    output wire [31:0] res,   // ALU result
    output wire zeroFlag,        // Zero flag
    output wire carryFlag        // Carry flag
);

// ALU operation code definitions
parameter ADD_OP = 4'b0000;
parameter SUB_OP = 4'b0001;
parameter AND_OP = 4'b0010;
parameter OR_OP  = 4'b0011;
parameter XOR_OP = 4'b0100;
parameter NOT_OP = 4'b0101;
parameter SLA_OP = 4'b0110;
parameter SRA_OP = 4'b0111;
parameter SRL_OP = 4'b1000;

reg [31:0] result;
// ALU control logic
always @(*)
begin
    case (aluOp)
        ADD_OP: result = operandA + operandB;
        SUB_OP: result = operandA - operandB;
        AND_OP: result = operandA & operandB;
        OR_OP:  result = operandA | operandB;
        XOR_OP: result = operandA ^ operandB;
        NOT_OP: result = ~operandA;
        SLA_OP: result = operandA << shiftAmount; // Arithmetic shift left
        SRA_OP: result = {operandA[31], operandA[31:1]}; // Arithmetic shift right
        SRL_OP: result = operandA >> shiftAmount; // Logical shift right
        default: result = 32'b0; // Default behavior for undefined opcode
    endcase
    
end

    assign zeroFlag = (result == 32'b0) ? 1'b1 : 1'b0;
    
    // Carry flag: Set if there's a carry-out in arithmetic operations
    assign carryFlag = (aluOp == ADD_OP && (result < operandA || result < operandB)) ? 1'b1 : 1'b0;
    assign res = enable? result:32'bz;

endmodule

ALU/alu_tb.v

module ALU_Testbench;

    reg [31:0] operandA;
    reg [31:0] operandB;
    reg [3:0] aluOp;
    reg shiftAmount;
    reg enable;
    wire [31:0] result;
    wire zeroFlag;
    wire carryFlag;

    // Instantiate the ALU module
    ALU UUT (
        .operandA(operandA),
        .operandB(operandB),
        .aluOp(aluOp),
        .enable(enable),
        .shiftAmount(shiftAmount),
        .res(result),
        .zeroFlag(zeroFlag),
        .carryFlag(carryFlag)
    );

    initial begin
        $dumpfile("dump.vcd");
        $dumpvars();
    end
    // Stimulus generation
    initial begin

        $monitor("%d  -   Result = %d  %b", $time, result, result);

        // Test case 0: ADD operation  with enable off
        enable=0;
        operandA = 32'd30;
        operandB = 32'd10;
        aluOp = 4'b0000; // ADD_OP
        shiftAmount = 0;
        #10; // Wait for a few simulation cycles

        // Test case 1: ADD operation
        enable=1;
        operandA = 32'd30;
        operandB = 32'd10;
        aluOp = 4'b0000; // ADD_OP
        shiftAmount = 0;
        #10; // Wait for a few simulation cycles
        

        // Test case 2: SUB operation
        operandA = 32'd30;
        operandB = 32'd10;
        aluOp = 4'b0001; // SUB_OP
        shiftAmount = 0;
        #10; // Wait for a few simulation cycles
        

        // Test case 3: AND operation
        operandA = 32'd14;
        operandB = 32'd3;
        aluOp = 4'b0010; // AND_OP
        shiftAmount = 0;
        #10; // Wait for a few simulation cycles
      
        // Test case 4: OR operation
        operandA = 32'd14;
        operandB = 32'd3;
        aluOp = 4'b0011; // OR_OP
        shiftAmount = 0;
        #10; // Wait for a few simulation cycles
        
        // Test case 5: XOR operation
        operandA = 32'd14;
        operandB = 32'd3;
        aluOp = 4'b0100; // XOR_OP
        shiftAmount = 0;
        #10; 

        // Test case 6: NOT operation
        operandA = 32'b11111111111111111111111111110000;
        operandB = 32'd3;
        aluOp = 4'b0101; 
        shiftAmount = 0;
        #10; 

        // Test case 7: SLA operation
        operandA = 32'd7;
        operandB = 32'd3;
        aluOp = 4'b0110; 
        shiftAmount = 1;
        #10; 

        // Test case 8: SRA operation
        operandA = {8'd255, 8'd255, 8'd255, 8'b11111110};
        operandB = 32'd3;
        aluOp = 4'b0111; 
        shiftAmount = 1;
        #10;
        
        // Test case 9: SRL operation
        operandA = 32'd14;
        operandB = 32'd3;
        aluOp = 4'b1000; 
        shiftAmount = 1;
        #10; // Wait for a few simulation cycles

        // Test case 10: ADD operation
        enable=1;
        operandA = 32'd30;
        operandB = 32'd70;
        aluOp = 4'b0000; // ADD_OP
        shiftAmount = 0;
        
        #100;
        
        
    end

endmodule

ALU/dump.vcd
$date
	Mon Oct 16 16:50:05 2023
$end
$version
	Icarus Verilog
$end
$timescale
	1s
$end
$scope module ALU_Testbench $end
$var wire 1 ! zeroFlag $end
$var wire 32 " result [31:0] $end
$var wire 1 # carryFlag $end
$var reg 4 $ aluOp [3:0] $end
$var reg 1 % enable $end
$var reg 32 & operandA [31:0] $end
$var reg 32 ' operandB [31:0] $end
$var reg 1 ( shiftAmount $end
$scope module UUT $end
$var wire 4 ) aluOp [3:0] $end
$var wire 1 % enable $end
$var wire 32 * operandA [31:0] $end
$var wire 32 + operandB [31:0] $end
$var wire 1 ( shiftAmount $end
$var wire 1 ! zeroFlag $end
$var wire 32 , res [31:0] $end
$var wire 1 # carryFlag $end
$var parameter 4 - ADD_OP $end
$var parameter 4 . AND_OP $end
$var parameter 4 / NOT_OP $end
$var parameter 4 0 OR_OP $end
$var parameter 4 1 SLA_OP $end
$var parameter 4 2 SRA_OP $end
$var parameter 4 3 SRL_OP $end
$var parameter 4 4 SUB_OP $end
$var parameter 4 5 XOR_OP $end
$var reg 32 6 result [31:0] $end
$upscope $end
$upscope $end
$enddefinitions $end
$comment Show the parameter values. $end
$dumpall
b100 5
b1 4
b1000 3
b111 2
b110 1
b11 0
b101 /
b10 .
b0 -
$end
#0
$dumpvars
b101000 6
bz ,
b1010 +
b11110 *
b0 )
0(
b1010 '
b11110 &
0%
b0 $
0#
bz "
0!
$end
#10
b101000 "
b101000 ,
1%
#20
b10100 "
b10100 ,
b10100 6
b1 $
b1 )
#30
b10 "
b10 ,
b10 6
b10 $
b10 )
b11 '
b11 +
b1110 &
b1110 *
#40
b1111 "
b1111 ,
b1111 6
b11 $
b11 )
#50
b1101 "
b1101 ,
b1101 6
b100 $
b100 )
#60
b1111 "
b1111 ,
b1111 6
b101 $
b101 )
b11111111111111111111111111110000 &
b11111111111111111111111111110000 *
#70
b1110 "
b1110 ,
b1110 6
1(
b110 $
b110 )
b111 &
b111 *
#80
b11111111111111111111111111111111 "
b11111111111111111111111111111111 ,
b11111111111111111111111111111111 6
b111 $
b111 )
b11111111111111111111111111111110 &
b11111111111111111111111111111110 *
#90
b111 "
b111 ,
b111 6
b1000 $
b1000 )
b1110 &
b1110 *
#100
b1100100 "
b1100100 ,
b1100100 6
0(
b0 $
b0 )
b1000110 '
b1000110 +
b11110 &
b11110 *
